typtop/__init__.py
typtop/config.py
typtop/cryptography_pwpkcrypto.py
typtop/dbaccess.py
typtop/dbutils.py
typtop/pw_pkcrypto.py
typtop/pycryptodome_pwpkcrypto.py
typtop/send_typo_log.py
typtop/typtops.py
typtop/typtopserver.crt
typtop/validate_parent.py
typtop-0.2.11.dist-info/DESCRIPTION.rst
typtop-0.2.11.dist-info/LICENSE.txt
typtop-0.2.11.dist-info/METADATA
typtop-0.2.11.dist-info/RECORD
typtop-0.2.11.dist-info/WHEEL
typtop-0.2.11.dist-info/entry_points.txt
typtop-0.2.11.dist-info/metadata.json
typtop-0.2.11.dist-info/top_level.txt
typtop-0.2.11.dist-info/zip-safe
