Metadata-Version: 2.0
Name: typtop
Version: 0.2.11
Summary: Adaptive typo-tolerant password checking for Debian logins
Home-page: https://github.com/rchatterjee/pam-typopw
Author: Rahul Chatterjee, Yuval Pnueli
Author-email: rc737@cornell.edu
License: MIT
Download-URL: https://github.com/rchatterjee/pam-typopw/tarball/0.2.11
Keywords: Password,typo-tolerance,login-with-errors,Login
Platform: UNKNOWN
Classifier: Development Status :: 4 - Beta
Requires-Dist: cryptography (==1.8.1)
Requires-Dist: distro (==1.0.2)
Requires-Dist: pyyaml (==3.12)
Requires-Dist: requests (==2.13)
Requires-Dist: word2keypress (>=1.0.10)
Requires-Dist: zxcvbn-python (==4.4.14)
